<golproperties golId="9" golType="PCB">
<scheme>defscheme</scheme>
<bitmap memory="Internal">No_Train.bmp</bitmap>
<scale>
<list>0</list>
<list>1</list>
<list>2</list>
</scale>
<state>
<list>0</list>
<list>enabled</list>
<list>disabled</list>
</state>
<visible>
<list>0</list>
<list>true</list>
<list>false</list>
</visible>
<frame>
<list>0</list>
<list>disabled</list>
<list>enabled</list>
</frame>
<bottom>271</bottom>
<right>196</right>
<top>232</top>
<left>134</left>
<name>PCB_336</name>
</golproperties>
